sigmoidcolon/__init__.py
sigmoidcolon/colon.py
sigmoidcolon/functional.py
sigmoidcolon-0.0.2.dist-info/LICENSE
sigmoidcolon-0.0.2.dist-info/METADATA
sigmoidcolon-0.0.2.dist-info/WHEEL
sigmoidcolon-0.0.2.dist-info/top_level.txt
sigmoidcolon-0.0.2.dist-info/RECORD
